{
  "$schema": "https://raw.githubusercontent.com/spdx/spdx-spec/v2.2.1/schemas/spdx-schema.json",
  "spdxVersion": "SPDX-2.2",
  "dataLicense": "CC0-1.0",
  "SPDXID": "SPDXRef-DOCUMENT",
  "documentNamespace": "https://spdx.org/spdxdocs/giflib-x64-windows-5.2.2-f3d9f762-fcd1-41a5-be29-84afad39ae63",
  "name": "giflib:x64-windows@5.2.2 2fb14b6948c08c13f5434919e38d1c7bd8e718e4c50a99ef9c5833de7b75d584",
  "creationInfo": {
    "creators": [
      "Tool: vcpkg-2024-12-09-1005b78fa1bf1dde1a20c2734cba4ea61ca94d9a"
    ],
    "created": "2024-12-14T05:33:53Z"
  },
  "relationships": [
    {
      "spdxElementId": "SPDXRef-port",
      "relationshipType": "GENERATES",
      "relatedSpdxElement": "SPDXRef-binary"
    },
    {
      "spdxElementId": "SPDXRef-port",
      "relationshipType": "CONTAINS",
      "relatedSpdxElement": "SPDXRef-file-0"
    },
    {
      "spdxElementId": "SPDXRef-port",
      "relationshipType": "CONTAINS",
      "relatedSpdxElement": "SPDXRef-file-1"
    },
    {
      "spdxElementId": "SPDXRef-port",
      "relationshipType": "CONTAINS",
      "relatedSpdxElement": "SPDXRef-file-2"
    },
    {
      "spdxElementId": "SPDXRef-port",
      "relationshipType": "CONTAINS",
      "relatedSpdxElement": "SPDXRef-file-3"
    },
    {
      "spdxElementId": "SPDXRef-port",
      "relationshipType": "CONTAINS",
      "relatedSpdxElement": "SPDXRef-file-4"
    },
    {
      "spdxElementId": "SPDXRef-port",
      "relationshipType": "CONTAINS",
      "relatedSpdxElement": "SPDXRef-file-5"
    },
    {
      "spdxElementId": "SPDXRef-port",
      "relationshipType": "CONTAINS",
      "relatedSpdxElement": "SPDXRef-file-6"
    },
    {
      "spdxElementId": "SPDXRef-binary",
      "relationshipType": "GENERATED_FROM",
      "relatedSpdxElement": "SPDXRef-port"
    },
    {
      "spdxElementId": "SPDXRef-file-0",
      "relationshipType": "CONTAINED_BY",
      "relatedSpdxElement": "SPDXRef-port"
    },
    {
      "spdxElementId": "SPDXRef-file-1",
      "relationshipType": "CONTAINED_BY",
      "relatedSpdxElement": "SPDXRef-port"
    },
    {
      "spdxElementId": "SPDXRef-file-2",
      "relationshipType": "CONTAINED_BY",
      "relatedSpdxElement": "SPDXRef-port"
    },
    {
      "spdxElementId": "SPDXRef-file-3",
      "relationshipType": "CONTAINED_BY",
      "relatedSpdxElement": "SPDXRef-port"
    },
    {
      "spdxElementId": "SPDXRef-file-4",
      "relationshipType": "CONTAINED_BY",
      "relatedSpdxElement": "SPDXRef-port"
    },
    {
      "spdxElementId": "SPDXRef-file-5",
      "relationshipType": "CONTAINED_BY",
      "relatedSpdxElement": "SPDXRef-port"
    },
    {
      "spdxElementId": "SPDXRef-file-6",
      "relationshipType": "CONTAINED_BY",
      "relatedSpdxElement": "SPDXRef-port"
    }
  ],
  "packages": [
    {
      "name": "giflib",
      "SPDXID": "SPDXRef-port",
      "versionInfo": "5.2.2",
      "downloadLocation": "git+https://github.com/Microsoft/vcpkg#ports/giflib",
      "homepage": "https://sourceforge.net/projects/giflib/",
      "licenseConcluded": "MIT",
      "licenseDeclared": "NOASSERTION",
      "copyrightText": "NOASSERTION",
      "description": "A library for reading and writing gif images.",
      "comment": "This is the port (recipe) consumed by vcpkg."
    },
    {
      "name": "giflib:x64-windows",
      "SPDXID": "SPDXRef-binary",
      "versionInfo": "2fb14b6948c08c13f5434919e38d1c7bd8e718e4c50a99ef9c5833de7b75d584",
      "downloadLocation": "NONE",
      "licenseConcluded": "MIT",
      "licenseDeclared": "NOASSERTION",
      "copyrightText": "NOASSERTION",
      "comment": "This is a binary package built by vcpkg."
    },
    {
      "SPDXID": "SPDXRef-resource-0",
      "name": "giflib-${VERSION}.tar.gz",
      "packageFileName": "giflib-${VERSION}.tar.gz",
      "downloadLocation": "https://sourceforge.net/projects/giflib/files//giflib-${VERSION}.tar.gz",
      "licenseConcluded": "NOASSERTION",
      "licenseDeclared": "NOASSERTION",
      "copyrightText": "NOASSERTION",
      "checksums": [
        {
          "algorithm": "SHA512",
          "checksumValue": "0865ab2b1904fa14640c655fdb14bb54244ad18a66e358565c00287875d00912343f9be8bfac7658cc0146200d626f7ec9160d7a339f20ba3be6b9941d73975f"
        }
      ]
    }
  ],
  "files": [
    {
      "fileName": "./D:/lenky_jpegli/vcpkg/ports/giflib/CMakeLists.txt",
      "SPDXID": "SPDXRef-file-0",
      "checksums": [
        {
          "algorithm": "SHA256",
          "checksumValue": "2262eb2fd03dbbeca9a669357a48eb31f34f971a42586180fe69bc6bfab01c54"
        }
      ],
      "licenseConcluded": "NOASSERTION",
      "copyrightText": "NOASSERTION"
    },
    {
      "fileName": "./D:/lenky_jpegli/vcpkg/ports/giflib/exports.def",
      "SPDXID": "SPDXRef-file-1",
      "checksums": [
        {
          "algorithm": "SHA256",
          "checksumValue": "c6c3dee34dde15b1474e937b4f70ed7ca67847a826af4db749a8c9f414fae2b1"
        }
      ],
      "licenseConcluded": "NOASSERTION",
      "copyrightText": "NOASSERTION"
    },
    {
      "fileName": "./D:/lenky_jpegli/vcpkg/ports/giflib/msvc.diff",
      "SPDXID": "SPDXRef-file-2",
      "checksums": [
        {
          "algorithm": "SHA256",
          "checksumValue": "494165202112a8158c2e4fce46d092ec8bca41dd96fed3f064071f6675aa5ec2"
        }
      ],
      "licenseConcluded": "NOASSERTION",
      "copyrightText": "NOASSERTION"
    },
    {
      "fileName": "./D:/lenky_jpegli/vcpkg/ports/giflib/portfile.cmake",
      "SPDXID": "SPDXRef-file-3",
      "checksums": [
        {
          "algorithm": "SHA256",
          "checksumValue": "7fe32fadc095e5c2cd75da86965b7018ed04056ee3aa14a440bb23f5f070c58f"
        }
      ],
      "licenseConcluded": "NOASSERTION",
      "copyrightText": "NOASSERTION"
    },
    {
      "fileName": "./D:/lenky_jpegli/vcpkg/ports/giflib/usage",
      "SPDXID": "SPDXRef-file-4",
      "checksums": [
        {
          "algorithm": "SHA256",
          "checksumValue": "76da1f15431142f10b07577a061a3028ad2e07090258533c24a59a8965e72abd"
        }
      ],
      "licenseConcluded": "NOASSERTION",
      "copyrightText": "NOASSERTION"
    },
    {
      "fileName": "./D:/lenky_jpegli/vcpkg/ports/giflib/vcpkg-cmake-wrapper.cmake",
      "SPDXID": "SPDXRef-file-5",
      "checksums": [
        {
          "algorithm": "SHA256",
          "checksumValue": "4b75f2118a5eb4a9b729ab7b9ea2c9c59b766887d20eaf6b349774d84ea439f9"
        }
      ],
      "licenseConcluded": "NOASSERTION",
      "copyrightText": "NOASSERTION"
    },
    {
      "fileName": "./D:/lenky_jpegli/vcpkg/ports/giflib/vcpkg.json",
      "SPDXID": "SPDXRef-file-6",
      "checksums": [
        {
          "algorithm": "SHA256",
          "checksumValue": "b8b7d2eed1c0c21bc772de44c7ddf9f4400fcf6567c62904ea85d7963252198b"
        }
      ],
      "licenseConcluded": "NOASSERTION",
      "copyrightText": "NOASSERTION"
    }
  ]
}
